llm_microscope/__init__.py
llm_microscope/functions.py
llm_microscope/logit_lens.py
llm_microscope-0.0.7.dist-info/LICENSE
llm_microscope-0.0.7.dist-info/METADATA
llm_microscope-0.0.7.dist-info/WHEEL
llm_microscope-0.0.7.dist-info/top_level.txt
llm_microscope-0.0.7.dist-info/RECORD
