Metadata-Version: 2.1
Name: llm-microscope
Version: 0.0.7
Summary: Official implementation of the LLM-Microscope package functions for the paper
Home-page: https://github.com/AIRI-Institute/LLM-Microscope
Author: Matvey Mikhalchuk
Author-email: mikhalchuk@airi.net
Classifier: Programming Language :: Python :: 3.10
Classifier: Operating System :: OS Independent
Requires-Python: >=3.10
License-File: LICENSE
Requires-Dist: torch >=2.1.0
Requires-Dist: matplotlib
